vizgrad/__init__.py
vizgrad/core.py
vizgrad-0.1.2.dist-info/licenses/LICENSE
vizgrad-0.1.2.dist-info/METADATA
vizgrad-0.1.2.dist-info/WHEEL
vizgrad-0.1.2.dist-info/top_level.txt
vizgrad-0.1.2.dist-info/RECORD
