Metadata-Version: 2.4
Name: vizgrad
Version: 0.1.2
Summary: A lightweight autograd engine with visualization capabilities for educational purposes
Author-email: Prabhanjana Ghuriki <ghurikiprabhanjana@gmail.com>
License: MIT
Project-URL: Homepage, https://github.com/GPrabhanjana/vizgrad
Project-URL: Repository, https://github.com/GPrabhanjana/vizgrad
Project-URL: Issues, https://github.com/GPrabhanjana/vizgrad/issues
Keywords: autograd,automatic-differentiation,deep-learning,visualization,education
Classifier: Development Status :: 3 - Alpha
Classifier: Intended Audience :: Education
Classifier: Intended Audience :: Developers
Classifier: Intended Audience :: Science/Research
Classifier: License :: OSI Approved :: MIT License
Classifier: Programming Language :: Python :: 3
Classifier: Programming Language :: Python :: 3.7
Classifier: Programming Language :: Python :: 3.8
Classifier: Programming Language :: Python :: 3.9
Classifier: Programming Language :: Python :: 3.10
Classifier: Programming Language :: Python :: 3.11
Classifier: Topic :: Scientific/Engineering :: Artificial Intelligence
Classifier: Topic :: Education
Requires-Python: >=3.7
License-File: LICENSE
Requires-Dist: numpy>=1.19.0
Requires-Dist: matplotlib>=3.3.0
Provides-Extra: dev
Requires-Dist: pytest>=6.0; extra == "dev"
Requires-Dist: pytest-cov>=2.0; extra == "dev"
Dynamic: license-file
